[{"host":{"consumption":0.0,"timestamp":1752677634.4122157,"components":{"disks":[]}},"consumers":[],"sockets":[]},{"host":{"consumption":1910632.0,"timestamp":1752677636.4453688,"components":{"disks":[{"disk_type":"Unknown","disk_mount_point":"/var/lib/docker/overlay2/29881552ac69e99b810a1f2713d18b93cfccaf9d4e725a065ab9208aecbcfeb3/merged","disk_is_removable":false,"disk_file_system":"overlay","disk_total_bytes":"204402401280","disk_available_bytes":"151172251648","disk_name":"overlay"}]}},"consumers":[{"exe":"/usr/bin/scaphandre","cmdline":"/usr/bin/scaphandrejson--containers-foutput/2025-07-16-165339.json","pid":593320,"resources_usage":null,"consumption":8840.402,"timestamp":1752677636.4452567,"container":null},{"exe":"/usr/bin/dockerd","cmdline":"/usr/bin/dockerd-Hfd://--containerd=/run/containerd/containerd.sock","pid":1316,"resources_usage":null,"consumption":1105.0503,"timestamp":1752677636.445221,"container":null},{"exe":"/usr/libexec/gsd-xsettings","cmdline":"/usr/libexec/gsd-xsettings","pid":2154,"resources_usage":null,"consumption":1105.0503,"timestamp":1752677636.4452865,"container":null},{"exe":"/usr/libexec/xdg-permission-store","cmdline":"/usr/libexec/xdg-permission-store","pid":1689,"resources_usage":null,"consumption":0.0,"timestamp":1752677636.4451585,"container":null},{"exe":"","cmdline":"","pid":589911,"resources_usage":null,"consumption":0.0,"timestamp":1752677636.4451602,"container":null},{"exe":"","cmdline":"","pid":72,"resources_usage":null,"consumption":0.0,"timestamp":1752677636.4451606,"container":null},{"exe":"","cmdline":"","pid":107,"resources_usage":null,"consumption":0.0,"timestamp":1752677636.4451613,"container":null},{"exe":"/usr/sbin/NetworkManager","cmdline":"/usr/sbin/NetworkManager--no-daemon","pid":728,"resources_usage":null,"consumption":0.0,"timestamp":1752677636.445162,"container":null},{"exe":"","cmdline":"","pid":43,"resources_usage":null,"consumption":0.0,"timestamp":1752677636.4451625,"container":null},{"exe":"","cmdline":"","pid":45,"resources_usage":null,"consumption":0.0,"timestamp":1752677636.445163,"container":null}],"sockets":[{"id":0,"consumption":683997.0,"domains":[{"name":"uncore","consumption":6809.0,"timestamp":1752677636.4155664},{"name":"core","consumption":161872.0,"timestamp":1752677636.4154687},{"name":"dram","consumption":311117.0,"timestamp":1752677636.4153082}],"timestamp":1752677636.4146256}]},{"host":{"consumption":2643337.0,"timestamp":1752677638.5146372,"components":{"disks":[{"disk_type":"Unknown","disk_mount_point":"/var/lib/docker/overlay2/29881552ac69e99b810a1f2713d18b93cfccaf9d4e725a065ab9208aecbcfeb3/merged","disk_is_removable":false,"disk_file_system":"overlay","disk_total_bytes":"204402401280","disk_available_bytes":"151172251648","disk_name":"overlay"}]}},"consumers":[{"exe":"/usr/bin/scaphandre","cmdline":"/usr/bin/scaphandrejson--containers-foutput/2025-07-16-165339.json","pid":593320,"resources_usage":null,"consumption":6377.17,"timestamp":1752677638.5145562,"container":null},{"exe":"/usr/bin/gnome-shell","cmdline":"/usr/bin/gnome-shell","pid":1992,"resources_usage":null,"consumption":1594.2925,"timestamp":1752677638.5145113,"container":null},{"exe":"","cmdline":"","pid":585643,"resources_usage":null,"consumption":1594.2925,"timestamp":1752677638.514532,"container":null},{"exe":"/usr/libexec/xdg-permission-store","cmdline":"/usr/libexec/xdg-permission-store","pid":1689,"resources_usage":null,"consumption":0.0,"timestamp":1752677638.5145085,"container":null},{"exe":"","cmdline":"","pid":589911,"resources_usage":null,"consumption":0.0,"timestamp":1752677638.514509,"container":null},{"exe":"","cmdline":"","pid":72,"resources_usage":null,"consumption":0.0,"timestamp":1752677638.5145092,"container":null},{"exe":"","cmdline":"","pid":107,"resources_usage":null,"consumption":0.0,"timestamp":1752677638.5145094,"container":null},{"exe":"/usr/sbin/NetworkManager","cmdline":"/usr/sbin/NetworkManager--no-daemon","pid":728,"resources_usage":null,"consumption":0.0,"timestamp":1752677638.5145097,"container":null},{"exe":"","cmdline":"","pid":43,"resources_usage":null,"consumption":0.0,"timestamp":1752677638.5145097,"container":null},{"exe":"","cmdline":"","pid":45,"resources_usage":null,"consumption":0.0,"timestamp":1752677638.51451,"container":null}],"sockets":[{"id":0,"consumption":851450.0,"domains":[{"name":"uncore","consumption":5716.0,"timestamp":1752677638.4655888},{"name":"core","consumption":146606.0,"timestamp":1752677638.4654171},{"name":"dram","consumption":292382.0,"timestamp":1752677638.465239}],"timestamp":1752677638.464561}]},{"host":{"consumption":2945323.0,"timestamp":1752677640.5621002,"components":{"disks":[{"disk_type":"Unknown","disk_mount_point":"/var/lib/docker/overlay2/29881552ac69e99b810a1f2713d18b93cfccaf9d4e725a065ab9208aecbcfeb3/merged","disk_is_removable":false,"disk_file_system":"overlay","disk_total_bytes":"204402401280","disk_available_bytes":"151172247552","disk_name":"overlay"}]}},"consumers":[{"exe":"/usr/bin/scaphandre","cmdline":"/usr/bin/scaphandrejson--containers-foutput/2025-07-16-165339.json","pid":593320,"resources_usage":null,"consumption":9012.616,"timestamp":1752677640.561943,"container":null},{"exe":"/usr/lib/xorg/Xorg","cmdline":"/usr/lib/xorg/Xorgvt2-displayfd3-auth/run/user/1000/gdm/Xauthority-nolistentcp-backgroundnone-noreset-keeptty-novtswitch-verbose3","pid":1680,"resources_usage":null,"consumption":3605.0466,"timestamp":1752677640.5618825,"container":null},{"exe":"/usr/bin/gnome-shell","cmdline":"/usr/bin/gnome-shell","pid":1992,"resources_usage":null,"consumption":1802.5233,"timestamp":1752677640.561872,"container":null},{"exe":"/usr/bin/containerd","cmdline":"/usr/bin/containerd","pid":774,"resources_usage":null,"consumption":1802.5233,"timestamp":1752677640.5619633,"container":null},{"exe":"/usr/libexec/xdg-permission-store","cmdline":"/usr/libexec/xdg-permission-store","pid":1689,"resources_usage":null,"consumption":0.0,"timestamp":1752677640.5618675,"container":null},{"exe":"","cmdline":"","pid":589911,"resources_usage":null,"consumption":0.0,"timestamp":1752677640.5618684,"container":null},{"exe":"","cmdline":"","pid":72,"resources_usage":null,"consumption":0.0,"timestamp":1752677640.561869,"container":null},{"exe":"","cmdline":"","pid":107,"resources_usage":null,"consumption":0.0,"timestamp":1752677640.5618694,"container":null},{"exe":"/usr/sbin/NetworkManager","cmdline":"/usr/sbin/NetworkManager--no-daemon","pid":728,"resources_usage":null,"consumption":0.0,"timestamp":1752677640.5618696,"container":null},{"exe":"","cmdline":"","pid":43,"resources_usage":null,"consumption":0.0,"timestamp":1752677640.56187,"container":null}],"sockets":[{"id":0,"consumption":923605.0,"domains":[{"name":"uncore","consumption":6314.0,"timestamp":1752677640.5343003},{"name":"core","consumption":198118.0,"timestamp":1752677640.5341282},{"name":"dram","consumption":293297.0,"timestamp":1752677640.5339556}],"timestamp":1752677640.5332355}]},{"host":{"consumption":3343724.0,"timestamp":1752677642.6404912,"components":{"disks":[{"disk_type":"Unknown","disk_mount_point":"/var/lib/docker/overlay2/29881552ac69e99b810a1f2713d18b93cfccaf9d4e725a065ab9208aecbcfeb3/merged","disk_is_removable":false,"disk_file_system":"overlay","disk_total_bytes":"204402401280","disk_available_bytes":"151172247552","disk_name":"overlay"}]}},"consumers":[{"exe":"/usr/bin/scaphandre","cmdline":"/usr/bin/scaphandrejson--containers-foutput/2025-07-16-165339.json","pid":593320,"resources_usage":null,"consumption":14057.699,"timestamp":1752677642.640378,"container":null},{"exe":"/home/youssef/.asdf/installs/python/3.12.3/bin/python3.12","cmdline":"/home/youssef/web-server-benchmarks/srv/bin/python3./web-socket/measure_websocket.py--server_imagews-nginx-tornado-self--patternburst--modeecho--clients5--size_kb8--bursts3--interval0.5--output_csvresults/2025-07-16_090602/websocket/ws-nginx-tornado-self_payload_sweep.csv--measurement_typepayload_5_8","pid":593166,"resources_usage":null,"consumption":10041.213,"timestamp":1752677642.6403677,"container":null},{"exe":"/usr/libexec/gnome-terminal-server","cmdline":"/usr/libexec/gnome-terminal-server","pid":9853,"resources_usage":null,"consumption":2008.2427,"timestamp":1752677642.6402886,"container":null},{"exe":"/usr/bin/python3.11","cmdline":"python3/app/websocket_server.py","pid":593308,"resources_usage":null,"consumption":2008.2427,"timestamp":1752677642.6402893,"container":{"name":"ws-nginx-tornado-self","id":"119ed236be5949886d54ae33e7481051f43086613dffe26b1d9934e9f401947e","runtime":"unknown","scheduler":"docker"}},{"exe":"/usr/bin/containerd","cmdline":"/usr/bin/containerd","pid":774,"resources_usage":null,"consumption":2008.2427,"timestamp":1752677642.6404,"container":null},{"exe":"/usr/libexec/xdg-permission-store","cmdline":"/usr/libexec/xdg-permission-store","pid":1689,"resources_usage":null,"consumption":0.0,"timestamp":1752677642.640278,"container":null},{"exe":"","cmdline":"","pid":589911,"resources_usage":null,"consumption":0.0,"timestamp":1752677642.6402795,"container":null},{"exe":"","cmdline":"","pid":72,"resources_usage":null,"consumption":0.0,"timestamp":1752677642.6402802,"container":null},{"exe":"","cmdline":"","pid":107,"resources_usage":null,"consumption":0.0,"timestamp":1752677642.640281,"container":null},{"exe":"/usr/sbin/NetworkManager","cmdline":"/usr/sbin/NetworkManager--no-daemon","pid":728,"resources_usage":null,"consumption":0.0,"timestamp":1752677642.6402817,"container":null}],"sockets":[{"id":0,"consumption":1023741.0,"domains":[{"name":"uncore","consumption":13918.0,"timestamp":1752677642.5909564},{"name":"core","consumption":264955.0,"timestamp":1752677642.5907829},{"name":"dram","consumption":338553.0,"timestamp":1752677642.5906086}],"timestamp":1752677642.5899324}]},{"host":{"consumption":3123213.0,"timestamp":1752677644.6852288,"components":{"disks":[{"disk_type":"Unknown","disk_mount_point":"/var/lib/docker/overlay2/29881552ac69e99b810a1f2713d18b93cfccaf9d4e725a065ab9208aecbcfeb3/merged","disk_is_removable":false,"disk_file_system":"overlay","disk_total_bytes":"204402401280","disk_available_bytes":"151172243456","disk_name":"overlay"}]}},"consumers":[{"exe":"/usr/bin/scaphandre","cmdline":"/usr/bin/scaphandrejson--containers-foutput/2025-07-16-165339.json","pid":593320,"resources_usage":null,"consumption":9556.955,"timestamp":1752677644.6850874,"container":null},{"exe":"/usr/bin/gnome-shell","cmdline":"/usr/bin/gnome-shell","pid":1992,"resources_usage":null,"consumption":1911.3911,"timestamp":1752677644.685017,"container":null},{"exe":"/usr/bin/dockerd","cmdline":"/usr/bin/dockerd-Hfd://--containerd=/run/containerd/containerd.sock","pid":1316,"resources_usage":null,"consumption":1911.3911,"timestamp":1752677644.6850612,"container":null},{"exe":"/usr/libexec/xdg-permission-store","cmdline":"/usr/libexec/xdg-permission-store","pid":1689,"resources_usage":null,"consumption":0.0,"timestamp":1752677644.6850123,"container":null},{"exe":"","cmdline":"","pid":589911,"resources_usage":null,"consumption":0.0,"timestamp":1752677644.6850133,"container":null},{"exe":"","cmdline":"","pid":72,"resources_usage":null,"consumption":0.0,"timestamp":1752677644.6850138,"container":null},{"exe":"","cmdline":"","pid":107,"resources_usage":null,"consumption":0.0,"timestamp":1752677644.685014,"container":null},{"exe":"/usr/sbin/NetworkManager","cmdline":"/usr/sbin/NetworkManager--no-daemon","pid":728,"resources_usage":null,"consumption":0.0,"timestamp":1752677644.6850142,"container":null},{"exe":"","cmdline":"","pid":43,"resources_usage":null,"consumption":0.0,"timestamp":1752677644.685015,"container":null},{"exe":"","cmdline":"","pid":45,"resources_usage":null,"consumption":0.0,"timestamp":1752677644.685015,"container":null}],"sockets":[{"id":0,"consumption":909661.0,"domains":[{"name":"uncore","consumption":5217.0,"timestamp":1752677644.661627},{"name":"core","consumption":174256.0,"timestamp":1752677644.6615133},{"name":"dram","consumption":298405.0,"timestamp":1752677644.6613407}],"timestamp":1752677644.660593}]},{"host":{"consumption":2191298.0,"timestamp":1752677646.7309463,"components":{"disks":[{"disk_type":"Unknown","disk_mount_point":"/var/lib/docker/overlay2/29881552ac69e99b810a1f2713d18b93cfccaf9d4e725a065ab9208aecbcfeb3/merged","disk_is_removable":false,"disk_file_system":"overlay","disk_total_bytes":"204402401280","disk_available_bytes":"151172243456","disk_name":"overlay"}]}},"consumers":[{"exe":"/usr/bin/scaphandre","cmdline":"/usr/bin/scaphandrejson--containers-foutput/2025-07-16-165339.json","pid":593320,"resources_usage":null,"consumption":5360.9736,"timestamp":1752677646.730804,"container":null},{"exe":"/usr/lib/xorg/Xorg","cmdline":"/usr/lib/xorg/Xorgvt2-displayfd3-auth/run/user/1000/gdm/Xauthority-nolistentcp-backgroundnone-noreset-keeptty-novtswitch-verbose3","pid":1680,"resources_usage":null,"consumption":1340.2434,"timestamp":1752677646.7307453,"container":null},{"exe":"","cmdline":"","pid":587888,"resources_usage":null,"consumption":1340.2434,"timestamp":1752677646.7307742,"container":null},{"exe":"","cmdline":"","pid":575660,"resources_usage":null,"consumption":1340.2434,"timestamp":1752677646.730797,"container":null},{"exe":"/usr/libexec/xdg-permission-store","cmdline":"/usr/libexec/xdg-permission-store","pid":1689,"resources_usage":null,"consumption":0.0,"timestamp":1752677646.730728,"container":null},{"exe":"","cmdline":"","pid":589911,"resources_usage":null,"consumption":0.0,"timestamp":1752677646.730729,"container":null},{"exe":"","cmdline":"","pid":72,"resources_usage":null,"consumption":0.0,"timestamp":1752677646.7307296,"container":null},{"exe":"","cmdline":"","pid":107,"resources_usage":null,"consumption":0.0,"timestamp":1752677646.73073,"container":null},{"exe":"/usr/sbin/NetworkManager","cmdline":"/usr/sbin/NetworkManager--no-daemon","pid":728,"resources_usage":null,"consumption":0.0,"timestamp":1752677646.7307303,"container":null},{"exe":"","cmdline":"","pid":43,"resources_usage":null,"consumption":0.0,"timestamp":1752677646.7307308,"container":null}],"sockets":[{"id":0,"consumption":733637.0,"domains":[{"name":"uncore","consumption":1819.0,"timestamp":1752677646.7073646},{"name":"core","consumption":197008.0,"timestamp":1752677646.7071855},{"name":"dram","consumption":335000.0,"timestamp":1752677646.7070115}],"timestamp":1752677646.7063606}]},{"host":{"consumption":2734434.0,"timestamp":1752677648.8028824,"components":{"disks":[{"disk_type":"Unknown","disk_mount_point":"/var/lib/docker/overlay2/29881552ac69e99b810a1f2713d18b93cfccaf9d4e725a065ab9208aecbcfeb3/merged","disk_is_removable":false,"disk_file_system":"overlay","disk_total_bytes":"204402401280","disk_available_bytes":"151172239360","disk_name":"overlay"}]}},"consumers":[{"exe":"/usr/bin/scaphandre","cmdline":"/usr/bin/scaphandrejson--containers-foutput/2025-07-16-165339.json","pid":593320,"resources_usage":null,"consumption":6612.9,"timestamp":1752677648.8027277,"container":null},{"exe":"/usr/bin/gnome-shell","cmdline":"/usr/bin/gnome-shell","pid":1992,"resources_usage":null,"consumption":1653.225,"timestamp":1752677648.8026574,"container":null},{"exe":"/usr/libexec/gnome-terminal-server","cmdline":"/usr/libexec/gnome-terminal-server","pid":9853,"resources_usage":null,"consumption":1653.225,"timestamp":1752677648.8026595,"container":null},{"exe":"","cmdline":"","pid":590569,"resources_usage":null,"consumption":1653.225,"timestamp":1752677648.8026667,"container":null},{"exe":"/usr/lib/xorg/Xorg","cmdline":"/usr/lib/xorg/Xorgvt2-displayfd3-auth/run/user/1000/gdm/Xauthority-nolistentcp-backgroundnone-noreset-keeptty-novtswitch-verbose3","pid":1680,"resources_usage":null,"consumption":1653.225,"timestamp":1752677648.8026698,"container":null},{"exe":"/usr/libexec/xdg-permission-store","cmdline":"/usr/libexec/xdg-permission-store","pid":1689,"resources_usage":null,"consumption":0.0,"timestamp":1752677648.8026521,"container":null},{"exe":"","cmdline":"","pid":589911,"resources_usage":null,"consumption":0.0,"timestamp":1752677648.802653,"container":null},{"exe":"","cmdline":"","pid":72,"resources_usage":null,"consumption":0.0,"timestamp":1752677648.8026536,"container":null},{"exe":"","cmdline":"","pid":107,"resources_usage":null,"consumption":0.0,"timestamp":1752677648.8026538,"container":null},{"exe":"/usr/sbin/NetworkManager","cmdline":"/usr/sbin/NetworkManager--no-daemon","pid":728,"resources_usage":null,"consumption":0.0,"timestamp":1752677648.8026543,"container":null}],"sockets":[{"id":0,"consumption":880657.0,"domains":[{"name":"uncore","consumption":11052.0,"timestamp":1752677648.7506654},{"name":"core","consumption":147979.0,"timestamp":1752677648.750491},{"name":"dram","consumption":360779.0,"timestamp":1752677648.7503147}],"timestamp":1752677648.7496448}]},{"host":{"consumption":2813383.0,"timestamp":1752677650.850086,"components":{"disks":[{"disk_type":"Unknown","disk_mount_point":"/var/lib/docker/overlay2/29881552ac69e99b810a1f2713d18b93cfccaf9d4e725a065ab9208aecbcfeb3/merged","disk_is_removable":false,"disk_file_system":"overlay","disk_total_bytes":"204402401280","disk_available_bytes":"151172235264","disk_name":"overlay"}]}},"consumers":[{"exe":"/usr/bin/scaphandre","cmdline":"/usr/bin/scaphandrejson--containers-foutput/2025-07-16-165339.json","pid":593320,"resources_usage":null,"consumption":13757.375,"timestamp":1752677650.8500276,"container":null},{"exe":"/usr/bin/gnome-shell","cmdline":"/usr/bin/gnome-shell","pid":1992,"resources_usage":null,"consumption":3439.3438,"timestamp":1752677650.8499594,"container":null},{"exe":"","cmdline":"","pid":46,"resources_usage":null,"consumption":1719.6719,"timestamp":1752677650.8500216,"container":null},{"exe":"/usr/libexec/xdg-permission-store","cmdline":"/usr/libexec/xdg-permission-store","pid":1689,"resources_usage":null,"consumption":0.0,"timestamp":1752677650.8499541,"container":null},{"exe":"","cmdline":"","pid":589911,"resources_usage":null,"consumption":0.0,"timestamp":1752677650.849955,"container":null},{"exe":"","cmdline":"","pid":72,"resources_usage":null,"consumption":0.0,"timestamp":1752677650.8499558,"container":null},{"exe":"","cmdline":"","pid":107,"resources_usage":null,"consumption":0.0,"timestamp":1752677650.8499563,"container":null},{"exe":"/usr/sbin/NetworkManager","cmdline":"/usr/sbin/NetworkManager--no-daemon","pid":728,"resources_usage":null,"consumption":0.0,"timestamp":1752677650.8499565,"container":null},{"exe":"","cmdline":"","pid":43,"resources_usage":null,"consumption":0.0,"timestamp":1752677650.8499572,"container":null},{"exe":"","cmdline":"","pid":45,"resources_usage":null,"consumption":0.0,"timestamp":1752677650.8499575,"container":null}],"sockets":[{"id":0,"consumption":831871.0,"domains":[{"name":"uncore","consumption":5980.0,"timestamp":1752677650.8224702},{"name":"core","consumption":112595.0,"timestamp":1752677650.8222895},{"name":"dram","consumption":294981.0,"timestamp":1752677650.8221135}],"timestamp":1752677650.8214154}]}]