[{"host":{"consumption":0.0,"timestamp":1752677876.3845654,"components":{"disks":[]}},"consumers":[],"sockets":[]},{"host":{"consumption":2804303.0,"timestamp":1752677878.439229,"components":{"disks":[{"disk_type":"Unknown","disk_mount_point":"/var/lib/docker/overlay2/b23f7a09f8a8680f08dfd7caaf098bf1112de0e21cb81f39b2ca2739e77c968a/merged","disk_is_removable":false,"disk_file_system":"overlay","disk_total_bytes":"204402401280","disk_available_bytes":"151172120576","disk_name":"overlay"}]}},"consumers":[{"exe":"/usr/bin/scaphandre","cmdline":"/usr/bin/scaphandrejson--containers-foutput/2025-07-16-165741.json","pid":595511,"resources_usage":null,"consumption":7957.727,"timestamp":1752677878.43905,"container":null},{"exe":"/usr/libexec/gnome-terminal-server","cmdline":"/usr/libexec/gnome-terminal-server","pid":9853,"resources_usage":null,"consumption":1591.5454,"timestamp":1752677878.439042,"container":null},{"exe":"/usr/bin/gnome-shell","cmdline":"/usr/bin/gnome-shell","pid":1992,"resources_usage":null,"consumption":1591.5454,"timestamp":1752677878.439055,"container":null},{"exe":"/usr/lib/erlang/erts-13.1.5/bin/beam.smp","cmdline":"/usr/lib/erlang/erts-13.1.5/bin/beam.smp-Ktrue---root/usr/lib/erlang-bindir/usr/lib/erlang/erts-13.1.5/bin-prognameerl---home/root---noshell-noinput-pa/usr/lib/yaws/ebin-runyaws-conf/etc/yaws/yaws.conf-yawsencodinglatin1","pid":595427,"resources_usage":null,"consumption":1591.5454,"timestamp":1752677878.4390717,"container":{"name":"ws-yaws-27-self","id":"745fb2e3fb525475ad18975f6eaef7d5a581a4a065dc7049d0e5cd7af8a2e187","runtime":"unknown","scheduler":"docker"}},{"exe":"/usr/bin/dockerd","cmdline":"/usr/bin/dockerd-Hfd://--containerd=/run/containerd/containerd.sock","pid":1316,"resources_usage":null,"consumption":1591.5454,"timestamp":1752677878.4391053,"container":null},{"exe":"","cmdline":"","pid":487,"resources_usage":null,"consumption":0.0,"timestamp":1752677878.4390352,"container":null},{"exe":"","cmdline":"","pid":50,"resources_usage":null,"consumption":0.0,"timestamp":1752677878.4390361,"container":null},{"exe":"/usr/libexec/xdg-permission-store","cmdline":"/usr/libexec/xdg-permission-store","pid":1689,"resources_usage":null,"consumption":0.0,"timestamp":1752677878.4390366,"container":null},{"exe":"","cmdline":"","pid":23,"resources_usage":null,"consumption":0.0,"timestamp":1752677878.4390373,"container":null},{"exe":"/usr/libexec/gcr-ssh-agent","cmdline":"/usr/libexec/gcr-ssh-agent/run/user/1000/gcr","pid":1962,"resources_usage":null,"consumption":0.0,"timestamp":1752677878.4390376,"container":null}],"sockets":[{"id":0,"consumption":847262.0,"domains":[{"name":"uncore","consumption":7525.0,"timestamp":1752677878.387078},{"name":"core","consumption":124133.0,"timestamp":1752677878.386888},{"name":"dram","consumption":298601.0,"timestamp":1752677878.3867037}],"timestamp":1752677878.3860178}]},{"host":{"consumption":3287223.0,"timestamp":1752677880.4876707,"components":{"disks":[{"disk_type":"Unknown","disk_mount_point":"/var/lib/docker/overlay2/b23f7a09f8a8680f08dfd7caaf098bf1112de0e21cb81f39b2ca2739e77c968a/merged","disk_is_removable":false,"disk_file_system":"overlay","disk_total_bytes":"204402401280","disk_available_bytes":"151172120576","disk_name":"overlay"}]}},"consumers":[{"exe":"/usr/bin/scaphandre","cmdline":"/usr/bin/scaphandrejson--containers-foutput/2025-07-16-165741.json","pid":595511,"resources_usage":null,"consumption":16103.97,"timestamp":1752677880.4875479,"container":null},{"exe":"/usr/lib/erlang/erts-13.1.5/bin/beam.smp","cmdline":"/usr/lib/erlang/erts-13.1.5/bin/beam.smp-Ktrue---root/usr/lib/erlang-bindir/usr/lib/erlang/erts-13.1.5/bin-prognameerl---home/root---noshell-noinput-pa/usr/lib/yaws/ebin-runyaws-conf/etc/yaws/yaws.conf-yawsencodinglatin1","pid":595427,"resources_usage":null,"consumption":2012.9962,"timestamp":1752677880.4875646,"container":{"name":"ws-yaws-27-self","id":"745fb2e3fb525475ad18975f6eaef7d5a581a4a065dc7049d0e5cd7af8a2e187","runtime":"unknown","scheduler":"docker"}},{"exe":"/usr/bin/containerd","cmdline":"/usr/bin/containerd","pid":774,"resources_usage":null,"consumption":2012.9962,"timestamp":1752677880.48757,"container":null},{"exe":"/usr/lib/xorg/Xorg","cmdline":"/usr/lib/xorg/Xorgvt2-displayfd3-auth/run/user/1000/gdm/Xauthority-nolistentcp-backgroundnone-noreset-keeptty-novtswitch-verbose3","pid":1680,"resources_usage":null,"consumption":2012.9962,"timestamp":1752677880.487589,"container":null},{"exe":"","cmdline":"","pid":487,"resources_usage":null,"consumption":0.0,"timestamp":1752677880.487539,"container":null},{"exe":"","cmdline":"","pid":50,"resources_usage":null,"consumption":0.0,"timestamp":1752677880.4875395,"container":null},{"exe":"/usr/libexec/xdg-permission-store","cmdline":"/usr/libexec/xdg-permission-store","pid":1689,"resources_usage":null,"consumption":0.0,"timestamp":1752677880.4875398,"container":null},{"exe":"","cmdline":"","pid":23,"resources_usage":null,"consumption":0.0,"timestamp":1752677880.48754,"container":null},{"exe":"/usr/libexec/gcr-ssh-agent","cmdline":"/usr/libexec/gcr-ssh-agent/run/user/1000/gcr","pid":1962,"resources_usage":null,"consumption":0.0,"timestamp":1752677880.4875402,"container":null},{"exe":"/usr/libexec/gvfs-afc-volume-monitor","cmdline":"/usr/libexec/gvfs-afc-volume-monitor","pid":1769,"resources_usage":null,"consumption":0.0,"timestamp":1752677880.4875405,"container":null}],"sockets":[{"id":0,"consumption":1501338.0,"domains":[{"name":"uncore","consumption":7274.0,"timestamp":1752677880.4595873},{"name":"core","consumption":919261.0,"timestamp":1752677880.4594955},{"name":"dram","consumption":304902.0,"timestamp":1752677880.4593556}],"timestamp":1752677880.4587073}]},{"host":{"consumption":2932764.0,"timestamp":1752677882.531561,"components":{"disks":[{"disk_type":"Unknown","disk_mount_point":"/var/lib/docker/overlay2/b23f7a09f8a8680f08dfd7caaf098bf1112de0e21cb81f39b2ca2739e77c968a/merged","disk_is_removable":false,"disk_file_system":"overlay","disk_total_bytes":"204402401280","disk_available_bytes":"151172116480","disk_name":"overlay"}]}},"consumers":[{"exe":"/usr/bin/scaphandre","cmdline":"/usr/bin/scaphandrejson--containers-foutput/2025-07-16-165741.json","pid":595511,"resources_usage":null,"consumption":8963.215,"timestamp":1752677882.5314796,"container":null},{"exe":"/usr/lib/erlang/erts-13.1.5/bin/beam.smp","cmdline":"/usr/lib/erlang/erts-13.1.5/bin/beam.smp-Ktrue---root/usr/lib/erlang-bindir/usr/lib/erlang/erts-13.1.5/bin-prognameerl---home/root---noshell-noinput-pa/usr/lib/yaws/ebin-runyaws-conf/etc/yaws/yaws.conf-yawsencodinglatin1","pid":595427,"resources_usage":null,"consumption":3585.2861,"timestamp":1752677882.531497,"container":{"name":"ws-yaws-27-self","id":"745fb2e3fb525475ad18975f6eaef7d5a581a4a065dc7049d0e5cd7af8a2e187","runtime":"unknown","scheduler":"docker"}},{"exe":"/usr/bin/gnome-shell","cmdline":"/usr/bin/gnome-shell","pid":1992,"resources_usage":null,"consumption":1792.6431,"timestamp":1752677882.531483,"container":null},{"exe":"/usr/bin/containerd","cmdline":"/usr/bin/containerd","pid":774,"resources_usage":null,"consumption":1792.6431,"timestamp":1752677882.531503,"container":null},{"exe":"","cmdline":"","pid":487,"resources_usage":null,"consumption":0.0,"timestamp":1752677882.5314698,"container":null},{"exe":"","cmdline":"","pid":50,"resources_usage":null,"consumption":0.0,"timestamp":1752677882.5314703,"container":null},{"exe":"/usr/libexec/xdg-permission-store","cmdline":"/usr/libexec/xdg-permission-store","pid":1689,"resources_usage":null,"consumption":0.0,"timestamp":1752677882.5314705,"container":null},{"exe":"","cmdline":"","pid":23,"resources_usage":null,"consumption":0.0,"timestamp":1752677882.531471,"container":null},{"exe":"/usr/libexec/gcr-ssh-agent","cmdline":"/usr/libexec/gcr-ssh-agent/run/user/1000/gcr","pid":1962,"resources_usage":null,"consumption":0.0,"timestamp":1752677882.5314713,"container":null},{"exe":"/usr/libexec/gvfs-afc-volume-monitor","cmdline":"/usr/libexec/gvfs-afc-volume-monitor","pid":1769,"resources_usage":null,"consumption":0.0,"timestamp":1752677882.5314715,"container":null}],"sockets":[{"id":0,"consumption":893604.0,"domains":[{"name":"uncore","consumption":4533.0,"timestamp":1752677882.50578},{"name":"core","consumption":171044.0,"timestamp":1752677882.505604},{"name":"dram","consumption":293171.0,"timestamp":1752677882.5054312}],"timestamp":1752677882.5047617}]},{"host":{"consumption":8624582.0,"timestamp":1752677884.5954292,"components":{"disks":[{"disk_type":"Unknown","disk_mount_point":"/var/lib/docker/overlay2/b23f7a09f8a8680f08dfd7caaf098bf1112de0e21cb81f39b2ca2739e77c968a/merged","disk_is_removable":false,"disk_file_system":"overlay","disk_total_bytes":"204402401280","disk_available_bytes":"151172112384","disk_name":"overlay"}]}},"consumers":[{"exe":"/home/youssef/.asdf/installs/python/3.12.3/bin/python3.12","cmdline":"/home/youssef/web-server-benchmarks/srv/bin/python3./web-socket/measure_websocket.py--server_imagews-yaws-27-self--patternburst--modeecho--clients5000--size_kb8--bursts3--interval0.5--output_csvresults/2025-07-16_090602/websocket/ws-yaws-27-self_concurrency_sweep.csv--measurement_typeconcurrency_5000_8","pid":595233,"resources_usage":null,"consumption":355222.03,"timestamp":1752677884.5953174,"container":null},{"exe":"/usr/bin/scaphandre","cmdline":"/usr/bin/scaphandrejson--containers-foutput/2025-07-16-165741.json","pid":595511,"resources_usage":null,"consumption":26119.268,"timestamp":1752677884.5953035,"container":null},{"exe":"/usr/libexec/gnome-terminal-server","cmdline":"/usr/libexec/gnome-terminal-server","pid":9853,"resources_usage":null,"consumption":5223.853,"timestamp":1752677884.5952928,"container":null},{"exe":"","cmdline":"","pid":7389,"resources_usage":null,"consumption":5223.853,"timestamp":1752677884.595363,"container":null},{"exe":"/usr/lib/xorg/Xorg","cmdline":"/usr/lib/xorg/Xorgvt2-displayfd3-auth/run/user/1000/gdm/Xauthority-nolistentcp-backgroundnone-noreset-keeptty-novtswitch-verbose3","pid":1680,"resources_usage":null,"consumption":5223.853,"timestamp":1752677884.5953777,"container":null},{"exe":"","cmdline":"","pid":487,"resources_usage":null,"consumption":0.0,"timestamp":1752677884.5952828,"container":null},{"exe":"","cmdline":"","pid":50,"resources_usage":null,"consumption":0.0,"timestamp":1752677884.5952845,"container":null},{"exe":"/usr/libexec/xdg-permission-store","cmdline":"/usr/libexec/xdg-permission-store","pid":1689,"resources_usage":null,"consumption":0.0,"timestamp":1752677884.595285,"container":null},{"exe":"","cmdline":"","pid":23,"resources_usage":null,"consumption":0.0,"timestamp":1752677884.5952857,"container":null},{"exe":"/usr/libexec/gcr-ssh-agent","cmdline":"/usr/libexec/gcr-ssh-agent/run/user/1000/gcr","pid":1962,"resources_usage":null,"consumption":0.0,"timestamp":1752677884.5952861,"container":null}],"sockets":[{"id":0,"consumption":3766066.0,"domains":[{"name":"uncore","consumption":11919.0,"timestamp":1752677884.548924},{"name":"core","consumption":2913433.0,"timestamp":1752677884.5489142},{"name":"dram","consumption":394022.0,"timestamp":1752677884.5489035}],"timestamp":1752677884.5487664}]},{"host":{"consumption":20105836.0,"timestamp":1752677886.6403005,"components":{"disks":[{"disk_type":"Unknown","disk_mount_point":"/var/lib/docker/overlay2/b23f7a09f8a8680f08dfd7caaf098bf1112de0e21cb81f39b2ca2739e77c968a/merged","disk_is_removable":false,"disk_file_system":"overlay","disk_total_bytes":"204402401280","disk_available_bytes":"151172112384","disk_name":"overlay"}]}},"consumers":[{"exe":"/home/youssef/.asdf/installs/python/3.12.3/bin/python3.12","cmdline":"/home/youssef/web-server-benchmarks/srv/bin/python3./web-socket/measure_websocket.py--server_imagews-yaws-27-self--patternburst--modeecho--clients5000--size_kb8--bursts3--interval0.5--output_csvresults/2025-07-16_090602/websocket/ws-yaws-27-self_concurrency_sweep.csv--measurement_typeconcurrency_5000_8","pid":595233,"resources_usage":null,"consumption":2550927.8,"timestamp":1752677886.64006,"container":null},{"exe":"/usr/lib/erlang/erts-13.1.5/bin/beam.smp","cmdline":"/usr/lib/erlang/erts-13.1.5/bin/beam.smp-Ktrue---root/usr/lib/erlang-bindir/usr/lib/erlang/erts-13.1.5/bin-prognameerl---home/root---noshell-noinput-pa/usr/lib/yaws/ebin-runyaws-conf/etc/yaws/yaws.conf-yawsencodinglatin1","pid":595427,"resources_usage":null,"consumption":1407408.5,"timestamp":1752677886.6400878,"container":{"name":"ws-yaws-27-self","id":"745fb2e3fb525475ad18975f6eaef7d5a581a4a065dc7049d0e5cd7af8a2e187","runtime":"unknown","scheduler":"docker"}},{"exe":"/usr/bin/scaphandre","cmdline":"/usr/bin/scaphandrejson--containers-foutput/2025-07-16-165741.json","pid":595511,"resources_usage":null,"consumption":75396.88,"timestamp":1752677886.6400363,"container":null},{"exe":"/usr/bin/containerd","cmdline":"/usr/bin/containerd","pid":774,"resources_usage":null,"consumption":12566.146,"timestamp":1752677886.6401083,"container":null},{"exe":"","cmdline":"","pid":31,"resources_usage":null,"consumption":12566.146,"timestamp":1752677886.6401603,"container":null},{"exe":"","cmdline":"","pid":36,"resources_usage":null,"consumption":12566.146,"timestamp":1752677886.6401641,"container":null},{"exe":"","cmdline":"","pid":487,"resources_usage":null,"consumption":0.0,"timestamp":1752677886.6400015,"container":null},{"exe":"","cmdline":"","pid":50,"resources_usage":null,"consumption":0.0,"timestamp":1752677886.640003,"container":null},{"exe":"/usr/libexec/xdg-permission-store","cmdline":"/usr/libexec/xdg-permission-store","pid":1689,"resources_usage":null,"consumption":0.0,"timestamp":1752677886.6400037,"container":null},{"exe":"","cmdline":"","pid":23,"resources_usage":null,"consumption":0.0,"timestamp":1752677886.640005,"container":null}],"sockets":[{"id":0,"consumption":10729829.0,"domains":[{"name":"uncore","consumption":4643.0,"timestamp":1752677886.6127815},{"name":"core","consumption":9540144.0,"timestamp":1752677886.6127617},{"name":"dram","consumption":774620.0,"timestamp":1752677886.6127408}],"timestamp":1752677886.6124532}]},{"host":{"consumption":37437492.0,"timestamp":1752677888.771776,"components":{"disks":[{"disk_type":"Unknown","disk_mount_point":"/var/lib/docker/overlay2/b23f7a09f8a8680f08dfd7caaf098bf1112de0e21cb81f39b2ca2739e77c968a/merged","disk_is_removable":false,"disk_file_system":"overlay","disk_total_bytes":"204402401280","disk_available_bytes":"151172108288","disk_name":"overlay"}]}},"consumers":[{"exe":"/usr/lib/erlang/erts-13.1.5/bin/beam.smp","cmdline":"/usr/lib/erlang/erts-13.1.5/bin/beam.smp-Ktrue---root/usr/lib/erlang-bindir/usr/lib/erlang/erts-13.1.5/bin-prognameerl---home/root---noshell-noinput-pa/usr/lib/yaws/ebin-runyaws-conf/etc/yaws/yaws.conf-yawsencodinglatin1","pid":595427,"resources_usage":null,"consumption":20302812.0,"timestamp":1752677888.7685905,"container":{"name":"ws-yaws-27-self","id":"745fb2e3fb525475ad18975f6eaef7d5a581a4a065dc7049d0e5cd7af8a2e187","runtime":"unknown","scheduler":"docker"}},{"exe":"/home/youssef/.asdf/installs/python/3.12.3/bin/python3.12","cmdline":"/home/youssef/web-server-benchmarks/srv/bin/python3./web-socket/measure_websocket.py--server_imagews-yaws-27-self--patternburst--modeecho--clients5000--size_kb8--bursts3--interval0.5--output_csvresults/2025-07-16_090602/websocket/ws-yaws-27-self_concurrency_sweep.csv--measurement_typeconcurrency_5000_8","pid":595233,"resources_usage":null,"consumption":3971319.2,"timestamp":1752677888.7685704,"container":null},{"exe":"/usr/bin/docker-proxy","cmdline":"/usr/bin/docker-proxy-prototcp-host-ip::-host-port8001-container-ip172.17.0.2-container-port80-use-listen-fd","pid":595360,"resources_usage":null,"consumption":1249403.8,"timestamp":1752677888.768597,"container":null},{"exe":"/usr/bin/scaphandre","cmdline":"/usr/bin/scaphandrejson--containers-foutput/2025-07-16-165741.json","pid":595511,"resources_usage":null,"consumption":133864.69,"timestamp":1752677888.7685466,"container":null},{"exe":"","cmdline":"","pid":14,"resources_usage":null,"consumption":22310.781,"timestamp":1752677888.7685876,"container":null},{"exe":"","cmdline":"","pid":487,"resources_usage":null,"consumption":0.0,"timestamp":1752677888.768524,"container":null},{"exe":"","cmdline":"","pid":50,"resources_usage":null,"consumption":0.0,"timestamp":1752677888.7685251,"container":null},{"exe":"/usr/libexec/xdg-permission-store","cmdline":"/usr/libexec/xdg-permission-store","pid":1689,"resources_usage":null,"consumption":0.0,"timestamp":1752677888.7685256,"container":null},{"exe":"","cmdline":"","pid":23,"resources_usage":null,"consumption":0.0,"timestamp":1752677888.7685263,"container":null},{"exe":"/usr/libexec/gcr-ssh-agent","cmdline":"/usr/libexec/gcr-ssh-agent/run/user/1000/gcr","pid":1962,"resources_usage":null,"consumption":0.0,"timestamp":1752677888.7685268,"container":null}],"sockets":[{"id":0,"consumption":24759496.0,"domains":[{"name":"uncore","consumption":1567.0,"timestamp":1752677888.6761036},{"name":"core","consumption":23400732.0,"timestamp":1752677888.6760898},{"name":"dram","consumption":1068071.0,"timestamp":1752677888.6760771}],"timestamp":1752677888.6757815}]},{"host":{"consumption":33483602.0,"timestamp":1752677890.8649983,"components":{"disks":[{"disk_type":"Unknown","disk_mount_point":"/var/lib/docker/overlay2/b23f7a09f8a8680f08dfd7caaf098bf1112de0e21cb81f39b2ca2739e77c968a/merged","disk_is_removable":false,"disk_file_system":"overlay","disk_total_bytes":"204402401280","disk_available_bytes":"151172104192","disk_name":"overlay"}]}},"consumers":[{"exe":"/usr/lib/erlang/erts-13.1.5/bin/beam.smp","cmdline":"/usr/lib/erlang/erts-13.1.5/bin/beam.smp-Ktrue---root/usr/lib/erlang-bindir/usr/lib/erlang/erts-13.1.5/bin-prognameerl---home/root---noshell-noinput-pa/usr/lib/yaws/ebin-runyaws-conf/etc/yaws/yaws.conf-yawsencodinglatin1","pid":595427,"resources_usage":null,"consumption":18985958.0,"timestamp":1752677890.8648982,"container":{"name":"ws-yaws-27-self","id":"745fb2e3fb525475ad18975f6eaef7d5a581a4a065dc7049d0e5cd7af8a2e187","runtime":"unknown","scheduler":"docker"}},{"exe":"/home/youssef/.asdf/installs/python/3.12.3/bin/python3.12","cmdline":"/home/youssef/web-server-benchmarks/srv/bin/python3./web-socket/measure_websocket.py--server_imagews-yaws-27-self--patternburst--modeecho--clients5000--size_kb8--bursts3--interval0.5--output_csvresults/2025-07-16_090602/websocket/ws-yaws-27-self_concurrency_sweep.csv--measurement_typeconcurrency_5000_8","pid":595233,"resources_usage":null,"consumption":3793219.5,"timestamp":1752677890.864885,"container":null},{"exe":"/usr/bin/docker-proxy","cmdline":"/usr/bin/docker-proxy-prototcp-host-ip::-host-port8001-container-ip172.17.0.2-container-port80-use-listen-fd","pid":595360,"resources_usage":null,"consumption":1529203.8,"timestamp":1752677890.8649023,"container":null},{"exe":"/usr/bin/scaphandre","cmdline":"/usr/bin/scaphandrejson--containers-foutput/2025-07-16-165741.json","pid":595511,"resources_usage":null,"consumption":99298.94,"timestamp":1752677890.8648756,"container":null},{"exe":"/usr/bin/gnome-shell","cmdline":"/usr/bin/gnome-shell","pid":1992,"resources_usage":null,"consumption":39719.574,"timestamp":1752677890.8648808,"container":null},{"exe":"","cmdline":"","pid":41,"resources_usage":null,"consumption":39719.574,"timestamp":1752677890.864948,"container":null},{"exe":"","cmdline":"","pid":51,"resources_usage":null,"consumption":19859.787,"timestamp":1752677890.864871,"container":null},{"exe":"","cmdline":"","pid":21,"resources_usage":null,"consumption":19859.787,"timestamp":1752677890.8648772,"container":null},{"exe":"","cmdline":"","pid":15,"resources_usage":null,"consumption":19859.787,"timestamp":1752677890.8649073,"container":null},{"exe":"","cmdline":"","pid":31,"resources_usage":null,"consumption":19859.787,"timestamp":1752677890.8649306,"container":null}],"sockets":[{"id":0,"consumption":22768006.0,"domains":[{"name":"uncore","consumption":0.0,"timestamp":1752677890.8184202},{"name":"core","consumption":21294708.0,"timestamp":1752677890.8184118},{"name":"dram","consumption":1298292.0,"timestamp":1752677890.818403}],"timestamp":1752677890.8182251}]},{"host":{"consumption":5317663.0,"timestamp":1752677892.9092836,"components":{"disks":[{"disk_type":"Unknown","disk_mount_point":"/var/lib/docker/overlay2/b23f7a09f8a8680f08dfd7caaf098bf1112de0e21cb81f39b2ca2739e77c968a/merged","disk_is_removable":false,"disk_file_system":"overlay","disk_total_bytes":"204402401280","disk_available_bytes":"151172104192","disk_name":"overlay"}]}},"consumers":[{"exe":"/home/youssef/.asdf/installs/python/3.12.3/bin/python3.12","cmdline":"/home/youssef/web-server-benchmarks/srv/bin/python3./web-socket/measure_websocket.py--server_imagews-yaws-27-self--patternburst--modeecho--clients5000--size_kb8--bursts3--interval0.5--output_csvresults/2025-07-16_090602/websocket/ws-yaws-27-self_concurrency_sweep.csv--measurement_typeconcurrency_5000_8","pid":595233,"resources_usage":null,"consumption":146626.75,"timestamp":1752677892.909086,"container":null},{"exe":"/usr/lib/erlang/erts-13.1.5/bin/beam.smp","cmdline":"/usr/lib/erlang/erts-13.1.5/bin/beam.smp-Ktrue---root/usr/lib/erlang-bindir/usr/lib/erlang/erts-13.1.5/bin-prognameerl---home/root---noshell-noinput-pa/usr/lib/yaws/ebin-runyaws-conf/etc/yaws/yaws.conf-yawsencodinglatin1","pid":595427,"resources_usage":null,"consumption":74942.555,"timestamp":1752677892.9090998,"container":{"name":"ws-yaws-27-self","id":"745fb2e3fb525475ad18975f6eaef7d5a581a4a065dc7049d0e5cd7af8a2e187","runtime":"unknown","scheduler":"docker"}},{"exe":"/usr/bin/docker-proxy","cmdline":"/usr/bin/docker-proxy-prototcp-host-ip::-host-port8001-container-ip172.17.0.2-container-port80-use-listen-fd","pid":595360,"resources_usage":null,"consumption":26066.977,"timestamp":1752677892.9091036,"container":null},{"exe":"/usr/bin/scaphandre","cmdline":"/usr/bin/scaphandrejson--containers-foutput/2025-07-16-165741.json","pid":595511,"resources_usage":null,"consumption":16291.86,"timestamp":1752677892.9090767,"container":null},{"exe":"","cmdline":"","pid":46,"resources_usage":null,"consumption":3258.372,"timestamp":1752677892.909093,"container":null},{"exe":"/usr/bin/containerd","cmdline":"/usr/bin/containerd","pid":774,"resources_usage":null,"consumption":3258.372,"timestamp":1752677892.9091108,"container":null},{"exe":"","cmdline":"","pid":575660,"resources_usage":null,"consumption":3258.372,"timestamp":1752677892.9091542,"container":null},{"exe":"","cmdline":"","pid":487,"resources_usage":null,"consumption":0.0,"timestamp":1752677892.9090605,"container":null},{"exe":"","cmdline":"","pid":50,"resources_usage":null,"consumption":0.0,"timestamp":1752677892.9090614,"container":null},{"exe":"/usr/libexec/xdg-permission-store","cmdline":"/usr/libexec/xdg-permission-store","pid":1689,"resources_usage":null,"consumption":0.0,"timestamp":1752677892.9090621,"container":null}],"sockets":[{"id":0,"consumption":2449758.0,"domains":[{"name":"uncore","consumption":0.0,"timestamp":1752677892.8827846},{"name":"core","consumption":1562682.0,"timestamp":1752677892.8826182},{"name":"dram","consumption":502609.0,"timestamp":1752677892.8824534}],"timestamp":1752677892.881885}]},{"host":{"consumption":3137733.0,"timestamp":1752677894.9534488,"components":{"disks":[{"disk_type":"Unknown","disk_mount_point":"/var/lib/docker/overlay2/b23f7a09f8a8680f08dfd7caaf098bf1112de0e21cb81f39b2ca2739e77c968a/merged","disk_is_removable":false,"disk_file_system":"overlay","disk_total_bytes":"204402401280","disk_available_bytes":"151172100096","disk_name":"overlay"}]}},"consumers":[{"exe":"/usr/bin/scaphandre","cmdline":"/usr/bin/scaphandrejson--containers-foutput/2025-07-16-165741.json","pid":595511,"resources_usage":null,"consumption":13466.665,"timestamp":1752677894.9533286,"container":null},{"exe":"/usr/lib/erlang/erts-13.1.5/bin/beam.smp","cmdline":"/usr/lib/erlang/erts-13.1.5/bin/beam.smp-Ktrue---root/usr/lib/erlang-bindir/usr/lib/erlang/erts-13.1.5/bin-prognameerl---home/root---noshell-noinput-pa/usr/lib/yaws/ebin-runyaws-conf/etc/yaws/yaws.conf-yawsencodinglatin1","pid":595427,"resources_usage":null,"consumption":3847.6187,"timestamp":1752677894.9533508,"container":{"name":"ws-yaws-27-self","id":"745fb2e3fb525475ad18975f6eaef7d5a581a4a065dc7049d0e5cd7af8a2e187","runtime":"unknown","scheduler":"docker"}},{"exe":"/usr/bin/dockerd","cmdline":"/usr/bin/dockerd-Hfd://--containerd=/run/containerd/containerd.sock","pid":1316,"resources_usage":null,"consumption":3847.6187,"timestamp":1752677894.9533887,"container":null},{"exe":"","cmdline":"","pid":590275,"resources_usage":null,"consumption":1923.8093,"timestamp":1752677894.9533188,"container":null},{"exe":"","cmdline":"","pid":487,"resources_usage":null,"consumption":0.0,"timestamp":1752677894.9533129,"container":null},{"exe":"","cmdline":"","pid":50,"resources_usage":null,"consumption":0.0,"timestamp":1752677894.9533136,"container":null},{"exe":"/usr/libexec/xdg-permission-store","cmdline":"/usr/libexec/xdg-permission-store","pid":1689,"resources_usage":null,"consumption":0.0,"timestamp":1752677894.953314,"container":null},{"exe":"","cmdline":"","pid":23,"resources_usage":null,"consumption":0.0,"timestamp":1752677894.9533148,"container":null},{"exe":"/usr/libexec/gcr-ssh-agent","cmdline":"/usr/libexec/gcr-ssh-agent/run/user/1000/gcr","pid":1962,"resources_usage":null,"consumption":0.0,"timestamp":1752677894.953315,"container":null},{"exe":"/usr/libexec/gvfs-afc-volume-monitor","cmdline":"/usr/libexec/gvfs-afc-volume-monitor","pid":1769,"resources_usage":null,"consumption":0.0,"timestamp":1752677894.9533157,"container":null}],"sockets":[{"id":0,"consumption":963115.0,"domains":[{"name":"uncore","consumption":0.0,"timestamp":1752677894.9266758},{"name":"core","consumption":238987.0,"timestamp":1752677894.9264998},{"name":"dram","consumption":289755.0,"timestamp":1752677894.926324}],"timestamp":1752677894.92571}]},{"host":{"consumption":3010471.0,"timestamp":1752677896.9956725,"components":{"disks":[{"disk_type":"Unknown","disk_mount_point":"/var/lib/docker/overlay2/b23f7a09f8a8680f08dfd7caaf098bf1112de0e21cb81f39b2ca2739e77c968a/merged","disk_is_removable":false,"disk_file_system":"overlay","disk_total_bytes":"204402401280","disk_available_bytes":"151172096000","disk_name":"overlay"}]}},"consumers":[{"exe":"/usr/bin/scaphandre","cmdline":"/usr/bin/scaphandrejson--containers-foutput/2025-07-16-165741.json","pid":595511,"resources_usage":null,"consumption":11047.6,"timestamp":1752677896.9955096,"container":null},{"exe":"/usr/lib/erlang/erts-13.1.5/bin/beam.smp","cmdline":"/usr/lib/erlang/erts-13.1.5/bin/beam.smp-Ktrue---root/usr/lib/erlang-bindir/usr/lib/erlang/erts-13.1.5/bin-prognameerl---home/root---noshell-noinput-pa/usr/lib/yaws/ebin-runyaws-conf/etc/yaws/yaws.conf-yawsencodinglatin1","pid":595427,"resources_usage":null,"consumption":7365.0664,"timestamp":1752677896.9955337,"container":{"name":"ws-yaws-27-self","id":"745fb2e3fb525475ad18975f6eaef7d5a581a4a065dc7049d0e5cd7af8a2e187","runtime":"unknown","scheduler":"docker"}},{"exe":"/usr/bin/gnome-shell","cmdline":"/usr/bin/gnome-shell","pid":1992,"resources_usage":null,"consumption":1841.2666,"timestamp":1752677896.995515,"container":null},{"exe":"/usr/lib/xorg/Xorg","cmdline":"/usr/lib/xorg/Xorgvt2-displayfd3-auth/run/user/1000/gdm/Xauthority-nolistentcp-backgroundnone-noreset-keeptty-novtswitch-verbose3","pid":1680,"resources_usage":null,"consumption":1841.2666,"timestamp":1752677896.9955711,"container":null},{"exe":"","cmdline":"","pid":487,"resources_usage":null,"consumption":0.0,"timestamp":1752677896.995494,"container":null},{"exe":"","cmdline":"","pid":50,"resources_usage":null,"consumption":0.0,"timestamp":1752677896.9954946,"container":null},{"exe":"/usr/libexec/xdg-permission-store","cmdline":"/usr/libexec/xdg-permission-store","pid":1689,"resources_usage":null,"consumption":0.0,"timestamp":1752677896.9954948,"container":null},{"exe":"","cmdline":"","pid":23,"resources_usage":null,"consumption":0.0,"timestamp":1752677896.9954956,"container":null},{"exe":"/usr/libexec/gcr-ssh-agent","cmdline":"/usr/libexec/gcr-ssh-agent/run/user/1000/gcr","pid":1962,"resources_usage":null,"consumption":0.0,"timestamp":1752677896.9954958,"container":null},{"exe":"/usr/libexec/gvfs-afc-volume-monitor","cmdline":"/usr/libexec/gvfs-afc-volume-monitor","pid":1769,"resources_usage":null,"consumption":0.0,"timestamp":1752677896.9954965,"container":null}],"sockets":[{"id":0,"consumption":896692.0,"domains":[{"name":"uncore","consumption":9014.0,"timestamp":1752677896.9715273},{"name":"core","consumption":157656.0,"timestamp":1752677896.9713705},{"name":"dram","consumption":301285.0,"timestamp":1752677896.971184}],"timestamp":1752677896.9704359}]},{"host":{"consumption":2973940.0,"timestamp":1752677899.0388463,"components":{"disks":[{"disk_type":"Unknown","disk_mount_point":"/var/lib/docker/overlay2/b23f7a09f8a8680f08dfd7caaf098bf1112de0e21cb81f39b2ca2739e77c968a/merged","disk_is_removable":false,"disk_file_system":"overlay","disk_total_bytes":"204402401280","disk_available_bytes":"151172091904","disk_name":"overlay"}]}},"consumers":[{"exe":"/usr/lib/erlang/erts-13.1.5/bin/beam.smp","cmdline":"/usr/lib/erlang/erts-13.1.5/bin/beam.smp-Ktrue---root/usr/lib/erlang-bindir/usr/lib/erlang/erts-13.1.5/bin-prognameerl---home/root---noshell-noinput-pa/usr/lib/yaws/ebin-runyaws-conf/etc/yaws/yaws.conf-yawsencodinglatin1","pid":595427,"resources_usage":null,"consumption":7289.069,"timestamp":1752677899.0386384,"container":{"name":"ws-yaws-27-self","id":"745fb2e3fb525475ad18975f6eaef7d5a581a4a065dc7049d0e5cd7af8a2e187","runtime":"unknown","scheduler":"docker"}},{"exe":"/usr/bin/scaphandre","cmdline":"/usr/bin/scaphandrejson--containers-foutput/2025-07-16-165741.json","pid":595511,"resources_usage":null,"consumption":5466.8013,"timestamp":1752677899.0385947,"container":null},{"exe":"/usr/libexec/gnome-terminal-server","cmdline":"/usr/libexec/gnome-terminal-server","pid":9853,"resources_usage":null,"consumption":1822.2672,"timestamp":1752677899.0385857,"container":null},{"exe":"","cmdline":"","pid":487,"resources_usage":null,"consumption":0.0,"timestamp":1752677899.0385768,"container":null},{"exe":"","cmdline":"","pid":50,"resources_usage":null,"consumption":0.0,"timestamp":1752677899.0385778,"container":null},{"exe":"/usr/libexec/xdg-permission-store","cmdline":"/usr/libexec/xdg-permission-store","pid":1689,"resources_usage":null,"consumption":0.0,"timestamp":1752677899.038578,"container":null},{"exe":"","cmdline":"","pid":23,"resources_usage":null,"consumption":0.0,"timestamp":1752677899.038579,"container":null},{"exe":"/usr/libexec/gcr-ssh-agent","cmdline":"/usr/libexec/gcr-ssh-agent/run/user/1000/gcr","pid":1962,"resources_usage":null,"consumption":0.0,"timestamp":1752677899.0385792,"container":null},{"exe":"/usr/libexec/gvfs-afc-volume-monitor","cmdline":"/usr/libexec/gvfs-afc-volume-monitor","pid":1769,"resources_usage":null,"consumption":0.0,"timestamp":1752677899.0385797,"container":null},{"exe":"","cmdline":"","pid":171,"resources_usage":null,"consumption":0.0,"timestamp":1752677899.0385802,"container":null}],"sockets":[{"id":0,"consumption":910670.0,"domains":[{"name":"uncore","consumption":6754.0,"timestamp":1752677899.0137331},{"name":"core","consumption":167547.0,"timestamp":1752677899.013546},{"name":"dram","consumption":296033.0,"timestamp":1752677899.013355}],"timestamp":1752677899.012597}]}]