[{"host":{"consumption":0.0,"timestamp":1752650748.168556,"components":{"disks":[]}},"consumers":[],"sockets":[]},{"host":{"consumption":2259033.0,"timestamp":1752650750.2232747,"components":{"disks":[{"disk_type":"Unknown","disk_mount_point":"/var/lib/docker/overlay2/71ddaf31366dee1c7efc1b8de12a1f706b48c8ce98f254146159398d39d4dafc/merged","disk_is_removable":false,"disk_file_system":"overlay","disk_total_bytes":"204402401280","disk_available_bytes":"151202000896","disk_name":"overlay"}]}},"consumers":[{"exe":"/usr/bin/scaphandre","cmdline":"/usr/bin/scaphandrejson--containers-foutput/2025-07-16-092538.json","pid":60719,"resources_usage":null,"consumption":7696.8755,"timestamp":1752650750.223192,"container":null},{"exe":"/usr/bin/dockerd","cmdline":"/usr/bin/dockerd-Hfd://--containerd=/run/containerd/containerd.sock","pid":1316,"resources_usage":null,"consumption":2565.625,"timestamp":1752650750.2231343,"container":null},{"exe":"/app/simple_cowboy_app/erts-15.2.7/bin/beam.smp","cmdline":"/app/simple_cowboy_app/bin/simple_cowboy_app-Bd-Cmulti_time_warp---root/app/simple_cowboy_app-bindir/app/simple_cowboy_app/erts-15.2.7/bin-prognameapp/simple_cowboy_app/bin/simple_cowboy_app---home/root---noshell-noinput-boot/app/simple_cowboy_app/releases/0.1.0/start-modeembedded-boot_varSYSTEM_LIB_DIR/app/simple_cowboy_app/lib-config/app/simple_cowboy_app/releases/0.1.0/sys.config-snamesimple_cowboy_app-setcookiesimple_cowboy_app----foreground--","pid":60531,"resources_usage":null,"consumption":2565.625,"timestamp":1752650750.2231948,"container":{"name":"st-cowboy-27-self","id":"9bee05275f2c658d0de20ed3de1f43b99572cc5e727ff38cd1371a8ae1720c93","runtime":"unknown","scheduler":"docker"}},{"exe":"/usr/lib/xorg/Xorg","cmdline":"/usr/lib/xorg/Xorgvt2-displayfd3-auth/run/user/1000/gdm/Xauthority-nolistentcp-backgroundnone-noreset-keeptty-novtswitch-verbose3","pid":1680,"resources_usage":null,"consumption":1282.8125,"timestamp":1752650750.2231164,"container":null},{"exe":"/usr/bin/containerd","cmdline":"/usr/bin/containerd","pid":774,"resources_usage":null,"consumption":1282.8125,"timestamp":1752650750.2231407,"container":null},{"exe":"/usr/bin/gnome-shell","cmdline":"/usr/bin/gnome-shell","pid":1992,"resources_usage":null,"consumption":1282.8125,"timestamp":1752650750.223172,"container":null},{"exe":"/usr/libexec/gnome-terminal-server","cmdline":"/usr/libexec/gnome-terminal-server","pid":9853,"resources_usage":null,"consumption":1282.8125,"timestamp":1752650750.2232018,"container":null},{"exe":"","cmdline":"","pid":6,"resources_usage":null,"consumption":0.0,"timestamp":1752650750.2231154,"container":null},{"exe":"/usr/sbin/cron","cmdline":"/usr/sbin/cron-f","pid":675,"resources_usage":null,"consumption":0.0,"timestamp":1752650750.2231174,"container":null},{"exe":"","cmdline":"","pid":171,"resources_usage":null,"consumption":0.0,"timestamp":1752650750.223118,"container":null}],"sockets":[{"id":0,"consumption":845128.0,"domains":[{"name":"uncore","consumption":9990.0,"timestamp":1752650750.1711297},{"name":"core","consumption":147277.0,"timestamp":1752650750.1709695},{"name":"dram","consumption":302802.0,"timestamp":1752650750.1708102}],"timestamp":1752650750.1701493}]},{"host":{"consumption":2350346.0,"timestamp":1752650752.270632,"components":{"disks":[{"disk_type":"Unknown","disk_mount_point":"/var/lib/docker/overlay2/71ddaf31366dee1c7efc1b8de12a1f706b48c8ce98f254146159398d39d4dafc/merged","disk_is_removable":false,"disk_file_system":"overlay","disk_total_bytes":"204402401280","disk_available_bytes":"151202000896","disk_name":"overlay"}]}},"consumers":[{"exe":"/usr/bin/scaphandre","cmdline":"/usr/bin/scaphandrejson--containers-foutput/2025-07-16-092538.json","pid":60719,"resources_usage":null,"consumption":10050.35,"timestamp":1752650752.270498,"container":null},{"exe":"/usr/lib/xorg/Xorg","cmdline":"/usr/lib/xorg/Xorgvt2-displayfd3-auth/run/user/1000/gdm/Xauthority-nolistentcp-backgroundnone-noreset-keeptty-novtswitch-verbose3","pid":1680,"resources_usage":null,"consumption":1435.7642,"timestamp":1752650752.2704272,"container":null},{"exe":"/usr/bin/gnome-shell","cmdline":"/usr/bin/gnome-shell","pid":1992,"resources_usage":null,"consumption":1435.7642,"timestamp":1752650752.2704778,"container":null},{"exe":"/app/simple_cowboy_app/erts-15.2.7/bin/beam.smp","cmdline":"/app/simple_cowboy_app/bin/simple_cowboy_app-Bd-Cmulti_time_warp---root/app/simple_cowboy_app-bindir/app/simple_cowboy_app/erts-15.2.7/bin-prognameapp/simple_cowboy_app/bin/simple_cowboy_app---home/root---noshell-noinput-boot/app/simple_cowboy_app/releases/0.1.0/start-modeembedded-boot_varSYSTEM_LIB_DIR/app/simple_cowboy_app/lib-config/app/simple_cowboy_app/releases/0.1.0/sys.config-snamesimple_cowboy_app-setcookiesimple_cowboy_app----foreground--","pid":60531,"resources_usage":null,"consumption":1435.7642,"timestamp":1752650752.2705007,"container":{"name":"st-cowboy-27-self","id":"9bee05275f2c658d0de20ed3de1f43b99572cc5e727ff38cd1371a8ae1720c93","runtime":"unknown","scheduler":"docker"}},{"exe":"","cmdline":"","pid":6,"resources_usage":null,"consumption":0.0,"timestamp":1752650752.2704265,"container":null},{"exe":"/usr/sbin/cron","cmdline":"/usr/sbin/cron-f","pid":675,"resources_usage":null,"consumption":0.0,"timestamp":1752650752.2704277,"container":null},{"exe":"","cmdline":"","pid":171,"resources_usage":null,"consumption":0.0,"timestamp":1752650752.2704282,"container":null},{"exe":"","cmdline":"","pid":35,"resources_usage":null,"consumption":0.0,"timestamp":1752650752.2704284,"container":null},{"exe":"/usr/lib/systemd/systemd","cmdline":"(sd-pam)","pid":1613,"resources_usage":null,"consumption":0.0,"timestamp":1752650752.270429,"container":null},{"exe":"/usr/libexec/at-spi-bus-launcher","cmdline":"/usr/libexec/at-spi-bus-launcher","pid":1943,"resources_usage":null,"consumption":0.0,"timestamp":1752650752.2704291,"container":null}],"sockets":[{"id":0,"consumption":882313.0,"domains":[{"name":"uncore","consumption":14070.0,"timestamp":1752650752.2445974},{"name":"core","consumption":176381.0,"timestamp":1752650752.2444382},{"name":"dram","consumption":330126.0,"timestamp":1752650752.2442796}],"timestamp":1752650752.2435648}]},{"host":{"consumption":30846270.0,"timestamp":1752650754.3168557,"components":{"disks":[{"disk_type":"Unknown","disk_mount_point":"/var/lib/docker/overlay2/71ddaf31366dee1c7efc1b8de12a1f706b48c8ce98f254146159398d39d4dafc/merged","disk_is_removable":false,"disk_file_system":"overlay","disk_total_bytes":"204402401280","disk_available_bytes":"151201996800","disk_name":"overlay"}]}},"consumers":[{"exe":"/home/youssef/.asdf/installs/python/3.12.3/bin/python3.12","cmdline":"/home/youssef/web-server-benchmarks/srv/bin/python3./containers/measure_docker.py--server_imagest-cowboy-27-self--port_mapping8001:80--num_requests10000--output_csvresults/2025-07-16_090602/static/st-cowboy-27-self.csv","pid":60449,"resources_usage":null,"consumption":3418921.5,"timestamp":1752650754.3167927,"container":null},{"exe":"/app/simple_cowboy_app/erts-15.2.7/bin/beam.smp","cmdline":"/app/simple_cowboy_app/bin/simple_cowboy_app-Bd-Cmulti_time_warp---root/app/simple_cowboy_app-bindir/app/simple_cowboy_app/erts-15.2.7/bin-prognameapp/simple_cowboy_app/bin/simple_cowboy_app---home/root---noshell-noinput-boot/app/simple_cowboy_app/releases/0.1.0/start-modeembedded-boot_varSYSTEM_LIB_DIR/app/simple_cowboy_app/lib-config/app/simple_cowboy_app/releases/0.1.0/sys.config-snamesimple_cowboy_app-setcookiesimple_cowboy_app----foreground--","pid":60531,"resources_usage":null,"consumption":2564191.2,"timestamp":1752650754.3168194,"container":{"name":"st-cowboy-27-self","id":"9bee05275f2c658d0de20ed3de1f43b99572cc5e727ff38cd1371a8ae1720c93","runtime":"unknown","scheduler":"docker"}},{"exe":"/usr/bin/scaphandre","cmdline":"/usr/bin/scaphandrejson--containers-foutput/2025-07-16-092538.json","pid":60719,"resources_usage":null,"consumption":113964.055,"timestamp":1752650754.3168182,"container":null},{"exe":"","cmdline":"","pid":14,"resources_usage":null,"consumption":18994.01,"timestamp":1752650754.316802,"container":null},{"exe":"","cmdline":"","pid":36357,"resources_usage":null,"consumption":18994.01,"timestamp":1752650754.3168218,"container":null},{"exe":"","cmdline":"","pid":6,"resources_usage":null,"consumption":0.0,"timestamp":1752650754.3167775,"container":null},{"exe":"/usr/lib/xorg/Xorg","cmdline":"/usr/lib/xorg/Xorgvt2-displayfd3-auth/run/user/1000/gdm/Xauthority-nolistentcp-backgroundnone-noreset-keeptty-novtswitch-verbose3","pid":1680,"resources_usage":null,"consumption":0.0,"timestamp":1752650754.3167782,"container":null},{"exe":"/usr/sbin/cron","cmdline":"/usr/sbin/cron-f","pid":675,"resources_usage":null,"consumption":0.0,"timestamp":1752650754.3167787,"container":null},{"exe":"","cmdline":"","pid":171,"resources_usage":null,"consumption":0.0,"timestamp":1752650754.316779,"container":null},{"exe":"","cmdline":"","pid":35,"resources_usage":null,"consumption":0.0,"timestamp":1752650754.3167791,"container":null}],"sockets":[{"id":0,"consumption":20673382.0,"domains":[{"name":"uncore","consumption":5743.0,"timestamp":1752650754.295378},{"name":"core","consumption":19627148.0,"timestamp":1752650754.2953658},{"name":"dram","consumption":425325.0,"timestamp":1752650754.2953522}],"timestamp":1752650754.2951863}]},{"host":{"consumption":41420028.0,"timestamp":1752650756.3778656,"components":{"disks":[{"disk_type":"Unknown","disk_mount_point":"/var/lib/docker/overlay2/71ddaf31366dee1c7efc1b8de12a1f706b48c8ce98f254146159398d39d4dafc/merged","disk_is_removable":false,"disk_file_system":"overlay","disk_total_bytes":"204402401280","disk_available_bytes":"151201992704","disk_name":"overlay"}]}},"consumers":[{"exe":"/home/youssef/.asdf/installs/python/3.12.3/bin/python3.12","cmdline":"/home/youssef/web-server-benchmarks/srv/bin/python3./containers/measure_docker.py--server_imagest-cowboy-27-self--port_mapping8001:80--num_requests10000--output_csvresults/2025-07-16_090602/static/st-cowboy-27-self.csv","pid":60449,"resources_usage":null,"consumption":6216842.0,"timestamp":1752650756.3777633,"container":null},{"exe":"/app/simple_cowboy_app/erts-15.2.7/bin/beam.smp","cmdline":"/app/simple_cowboy_app/bin/simple_cowboy_app-Bd-Cmulti_time_warp---root/app/simple_cowboy_app-bindir/app/simple_cowboy_app/erts-15.2.7/bin-prognameapp/simple_cowboy_app/bin/simple_cowboy_app---home/root---noshell-noinput-boot/app/simple_cowboy_app/releases/0.1.0/start-modeembedded-boot_varSYSTEM_LIB_DIR/app/simple_cowboy_app/lib-config/app/simple_cowboy_app/releases/0.1.0/sys.config-snamesimple_cowboy_app-setcookiesimple_cowboy_app----foreground--","pid":60531,"resources_usage":null,"consumption":4221312.5,"timestamp":1752650756.3778148,"container":{"name":"st-cowboy-27-self","id":"9bee05275f2c658d0de20ed3de1f43b99572cc5e727ff38cd1371a8ae1720c93","runtime":"unknown","scheduler":"docker"}},{"exe":"/usr/bin/docker-proxy","cmdline":"/usr/bin/docker-proxy-prototcp-host-ip::-host-port8001-container-ip172.17.0.2-container-port80-use-listen-fd","pid":60579,"resources_usage":null,"consumption":1432687.9,"timestamp":1752650756.3778336,"container":null},{"exe":"/usr/bin/scaphandre","cmdline":"/usr/bin/scaphandrejson--containers-foutput/2025-07-16-092538.json","pid":60719,"resources_usage":null,"consumption":76751.14,"timestamp":1752650756.3778114,"container":null},{"exe":"","cmdline":"","pid":6,"resources_usage":null,"consumption":0.0,"timestamp":1752650756.3777282,"container":null},{"exe":"/usr/lib/xorg/Xorg","cmdline":"/usr/lib/xorg/Xorgvt2-displayfd3-auth/run/user/1000/gdm/Xauthority-nolistentcp-backgroundnone-noreset-keeptty-novtswitch-verbose3","pid":1680,"resources_usage":null,"consumption":0.0,"timestamp":1752650756.3777297,"container":null},{"exe":"/usr/sbin/cron","cmdline":"/usr/sbin/cron-f","pid":675,"resources_usage":null,"consumption":0.0,"timestamp":1752650756.3777304,"container":null},{"exe":"","cmdline":"","pid":171,"resources_usage":null,"consumption":0.0,"timestamp":1752650756.3777308,"container":null},{"exe":"","cmdline":"","pid":35,"resources_usage":null,"consumption":0.0,"timestamp":1752650756.3777313,"container":null},{"exe":"/usr/lib/systemd/systemd","cmdline":"(sd-pam)","pid":1613,"resources_usage":null,"consumption":0.0,"timestamp":1752650756.377732,"container":null}],"sockets":[{"id":0,"consumption":28979218.0,"domains":[{"name":"uncore","consumption":5002.0,"timestamp":1752650756.3329856},{"name":"core","consumption":27942244.0,"timestamp":1752650756.3329737},{"name":"dram","consumption":460067.0,"timestamp":1752650756.3329594}],"timestamp":1752650756.332755}]},{"host":{"consumption":36862770.0,"timestamp":1752650758.41903,"components":{"disks":[{"disk_type":"Unknown","disk_mount_point":"/var/lib/docker/overlay2/71ddaf31366dee1c7efc1b8de12a1f706b48c8ce98f254146159398d39d4dafc/merged","disk_is_removable":false,"disk_file_system":"overlay","disk_total_bytes":"204402401280","disk_available_bytes":"151201988608","disk_name":"overlay"}]}},"consumers":[{"exe":"/home/youssef/.asdf/installs/python/3.12.3/bin/python3.12","cmdline":"/home/youssef/web-server-benchmarks/srv/bin/python3./containers/measure_docker.py--server_imagest-cowboy-27-self--port_mapping8001:80--num_requests10000--output_csvresults/2025-07-16_090602/static/st-cowboy-27-self.csv","pid":60449,"resources_usage":null,"consumption":5438396.5,"timestamp":1752650758.418872,"container":null},{"exe":"/usr/bin/docker-proxy","cmdline":"/usr/bin/docker-proxy-prototcp-host-ip::-host-port8001-container-ip172.17.0.2-container-port80-use-listen-fd","pid":60579,"resources_usage":null,"consumption":5119829.0,"timestamp":1752650758.4189703,"container":null},{"exe":"/app/simple_cowboy_app/erts-15.2.7/bin/beam.smp","cmdline":"/app/simple_cowboy_app/bin/simple_cowboy_app-Bd-Cmulti_time_warp---root/app/simple_cowboy_app-bindir/app/simple_cowboy_app/erts-15.2.7/bin-prognameapp/simple_cowboy_app/bin/simple_cowboy_app---home/root---noshell-noinput-boot/app/simple_cowboy_app/releases/0.1.0/start-modeembedded-boot_varSYSTEM_LIB_DIR/app/simple_cowboy_app/lib-config/app/simple_cowboy_app/releases/0.1.0/sys.config-snamesimple_cowboy_app-setcookiesimple_cowboy_app----foreground--","pid":60531,"resources_usage":null,"consumption":3936579.8,"timestamp":1752650758.4189432,"container":{"name":"st-cowboy-27-self","id":"9bee05275f2c658d0de20ed3de1f43b99572cc5e727ff38cd1371a8ae1720c93","runtime":"unknown","scheduler":"docker"}},{"exe":"/usr/bin/scaphandre","cmdline":"/usr/bin/scaphandrejson--containers-foutput/2025-07-16-092538.json","pid":60719,"resources_usage":null,"consumption":91019.19,"timestamp":1752650758.41894,"container":null},{"exe":"","cmdline":"","pid":31,"resources_usage":null,"consumption":22754.797,"timestamp":1752650758.4188492,"container":null},{"exe":"/usr/libexec/gnome-terminal-server","cmdline":"/usr/libexec/gnome-terminal-server","pid":9853,"resources_usage":null,"consumption":22754.797,"timestamp":1752650758.4189532,"container":null},{"exe":"","cmdline":"","pid":6,"resources_usage":null,"consumption":0.0,"timestamp":1752650758.4188278,"container":null},{"exe":"/usr/lib/xorg/Xorg","cmdline":"/usr/lib/xorg/Xorgvt2-displayfd3-auth/run/user/1000/gdm/Xauthority-nolistentcp-backgroundnone-noreset-keeptty-novtswitch-verbose3","pid":1680,"resources_usage":null,"consumption":0.0,"timestamp":1752650758.418829,"container":null},{"exe":"/usr/sbin/cron","cmdline":"/usr/sbin/cron-f","pid":675,"resources_usage":null,"consumption":0.0,"timestamp":1752650758.4188316,"container":null},{"exe":"","cmdline":"","pid":171,"resources_usage":null,"consumption":0.0,"timestamp":1752650758.4188325,"container":null}],"sockets":[{"id":0,"consumption":24578928.0,"domains":[{"name":"uncore","consumption":6628.0,"timestamp":1752650758.3955998},{"name":"core","consumption":23221524.0,"timestamp":1752650758.3955717},{"name":"dram","consumption":923288.0,"timestamp":1752650758.3955357}],"timestamp":1752650758.3952718}]},{"host":{"consumption":29194916.0,"timestamp":1752650760.4656537,"components":{"disks":[{"disk_type":"Unknown","disk_mount_point":"/var/lib/docker/overlay2/71ddaf31366dee1c7efc1b8de12a1f706b48c8ce98f254146159398d39d4dafc/merged","disk_is_removable":false,"disk_file_system":"overlay","disk_total_bytes":"204402401280","disk_available_bytes":"151201988608","disk_name":"overlay"}]}},"consumers":[{"exe":"/usr/bin/docker-proxy","cmdline":"/usr/bin/docker-proxy-prototcp-host-ip::-host-port8001-container-ip172.17.0.2-container-port80-use-listen-fd","pid":60579,"resources_usage":null,"consumption":8269183.5,"timestamp":1752650760.465602,"container":null},{"exe":"/home/youssef/.asdf/installs/python/3.12.3/bin/python3.12","cmdline":"/home/youssef/web-server-benchmarks/srv/bin/python3./containers/measure_docker.py--server_imagest-cowboy-27-self--port_mapping8001:80--num_requests10000--output_csvresults/2025-07-16_090602/static/st-cowboy-27-self.csv","pid":60449,"resources_usage":null,"consumption":4260977.0,"timestamp":1752650760.4655046,"container":null},{"exe":"/app/simple_cowboy_app/erts-15.2.7/bin/beam.smp","cmdline":"/app/simple_cowboy_app/bin/simple_cowboy_app-Bd-Cmulti_time_warp---root/app/simple_cowboy_app-bindir/app/simple_cowboy_app/erts-15.2.7/bin-prognameapp/simple_cowboy_app/bin/simple_cowboy_app---home/root---noshell-noinput-boot/app/simple_cowboy_app/releases/0.1.0/start-modeembedded-boot_varSYSTEM_LIB_DIR/app/simple_cowboy_app/lib-config/app/simple_cowboy_app/releases/0.1.0/sys.config-snamesimple_cowboy_app-setcookiesimple_cowboy_app----foreground--","pid":60531,"resources_usage":null,"consumption":2961018.0,"timestamp":1752650760.4655757,"container":{"name":"st-cowboy-27-self","id":"9bee05275f2c658d0de20ed3de1f43b99572cc5e727ff38cd1371a8ae1720c93","runtime":"unknown","scheduler":"docker"}},{"exe":"/usr/bin/scaphandre","cmdline":"/usr/bin/scaphandrejson--containers-foutput/2025-07-16-092538.json","pid":60719,"resources_usage":null,"consumption":108329.92,"timestamp":1752650760.4655719,"container":null},{"exe":"/usr/lib/xorg/Xorg","cmdline":"/usr/lib/xorg/Xorgvt2-displayfd3-auth/run/user/1000/gdm/Xauthority-nolistentcp-backgroundnone-noreset-keeptty-novtswitch-verbose3","pid":1680,"resources_usage":null,"consumption":18054.988,"timestamp":1752650760.4654691,"container":null},{"exe":"/usr/bin/containerd","cmdline":"/usr/bin/containerd","pid":774,"resources_usage":null,"consumption":18054.988,"timestamp":1752650760.465499,"container":null},{"exe":"","cmdline":"","pid":46,"resources_usage":null,"consumption":18054.988,"timestamp":1752650760.465516,"container":null},{"exe":"/usr/bin/gnome-shell","cmdline":"/usr/bin/gnome-shell","pid":1992,"resources_usage":null,"consumption":18054.988,"timestamp":1752650760.4655406,"container":null},{"exe":"","cmdline":"","pid":6,"resources_usage":null,"consumption":0.0,"timestamp":1752650760.4654682,"container":null},{"exe":"/usr/sbin/cron","cmdline":"/usr/sbin/cron-f","pid":675,"resources_usage":null,"consumption":0.0,"timestamp":1752650760.465471,"container":null}],"sockets":[{"id":0,"consumption":16899072.0,"domains":[{"name":"uncore","consumption":5697.0,"timestamp":1752650760.441774},{"name":"core","consumption":15285743.0,"timestamp":1752650760.441748},{"name":"dram","consumption":1557053.0,"timestamp":1752650760.4417257}],"timestamp":1752650760.441465}]},{"host":{"consumption":24616238.0,"timestamp":1752650762.5516663,"components":{"disks":[{"disk_type":"Unknown","disk_mount_point":"/var/lib/docker/overlay2/71ddaf31366dee1c7efc1b8de12a1f706b48c8ce98f254146159398d39d4dafc/merged","disk_is_removable":false,"disk_file_system":"overlay","disk_total_bytes":"204402401280","disk_available_bytes":"151201984512","disk_name":"overlay"}]}},"consumers":[{"exe":"/usr/bin/docker-proxy","cmdline":"/usr/bin/docker-proxy-prototcp-host-ip::-host-port8001-container-ip172.17.0.2-container-port80-use-listen-fd","pid":60579,"resources_usage":null,"consumption":5886163.5,"timestamp":1752650762.5515192,"container":null},{"exe":"/home/youssef/.asdf/installs/python/3.12.3/bin/python3.12","cmdline":"/home/youssef/web-server-benchmarks/srv/bin/python3./containers/measure_docker.py--server_imagest-cowboy-27-self--port_mapping8001:80--num_requests10000--output_csvresults/2025-07-16_090602/static/st-cowboy-27-self.csv","pid":60449,"resources_usage":null,"consumption":3033638.0,"timestamp":1752650762.551343,"container":null},{"exe":"/app/simple_cowboy_app/erts-15.2.7/bin/beam.smp","cmdline":"/app/simple_cowboy_app/bin/simple_cowboy_app-Bd-Cmulti_time_warp---root/app/simple_cowboy_app-bindir/app/simple_cowboy_app/erts-15.2.7/bin-prognameapp/simple_cowboy_app/bin/simple_cowboy_app---home/root---noshell-noinput-boot/app/simple_cowboy_app/releases/0.1.0/start-modeembedded-boot_varSYSTEM_LIB_DIR/app/simple_cowboy_app/lib-config/app/simple_cowboy_app/releases/0.1.0/sys.config-snamesimple_cowboy_app-setcookiesimple_cowboy_app----foreground--","pid":60531,"resources_usage":null,"consumption":2097889.0,"timestamp":1752650762.5514681,"container":{"name":"st-cowboy-27-self","id":"9bee05275f2c658d0de20ed3de1f43b99572cc5e727ff38cd1371a8ae1720c93","runtime":"unknown","scheduler":"docker"}},{"exe":"/usr/bin/scaphandre","cmdline":"/usr/bin/scaphandrejson--containers-foutput/2025-07-16-092538.json","pid":60719,"resources_usage":null,"consumption":90556.37,"timestamp":1752650762.5514617,"container":null},{"exe":"","cmdline":"","pid":15,"resources_usage":null,"consumption":15092.728,"timestamp":1752650762.5514057,"container":null},{"exe":"","cmdline":"","pid":6,"resources_usage":null,"consumption":0.0,"timestamp":1752650762.5512693,"container":null},{"exe":"/usr/lib/xorg/Xorg","cmdline":"/usr/lib/xorg/Xorgvt2-displayfd3-auth/run/user/1000/gdm/Xauthority-nolistentcp-backgroundnone-noreset-keeptty-novtswitch-verbose3","pid":1680,"resources_usage":null,"consumption":0.0,"timestamp":1752650762.5512717,"container":null},{"exe":"/usr/sbin/cron","cmdline":"/usr/sbin/cron-f","pid":675,"resources_usage":null,"consumption":0.0,"timestamp":1752650762.5512755,"container":null},{"exe":"","cmdline":"","pid":171,"resources_usage":null,"consumption":0.0,"timestamp":1752650762.551277,"container":null},{"exe":"","cmdline":"","pid":35,"resources_usage":null,"consumption":0.0,"timestamp":1752650762.5512779,"container":null}],"sockets":[{"id":0,"consumption":14385157.0,"domains":[{"name":"uncore","consumption":1640.0,"timestamp":1752650762.4883215},{"name":"core","consumption":12860590.0,"timestamp":1752650762.488149},{"name":"dram","consumption":1394863.0,"timestamp":1752650762.4879763}],"timestamp":1752650762.4872797}]},{"host":{"consumption":2559481.0,"timestamp":1752650764.6234136,"components":{"disks":[{"disk_type":"Unknown","disk_mount_point":"/var/lib/docker/overlay2/71ddaf31366dee1c7efc1b8de12a1f706b48c8ce98f254146159398d39d4dafc/merged","disk_is_removable":false,"disk_file_system":"overlay","disk_total_bytes":"204402401280","disk_available_bytes":"151201980416","disk_name":"overlay"}]}},"consumers":[{"exe":"/usr/bin/scaphandre","cmdline":"/usr/bin/scaphandrejson--containers-foutput/2025-07-16-092538.json","pid":60719,"resources_usage":null,"consumption":18468.895,"timestamp":1752650764.6233509,"container":null},{"exe":"/usr/bin/dockerd","cmdline":"/usr/bin/dockerd-Hfd://--containerd=/run/containerd/containerd.sock","pid":1316,"resources_usage":null,"consumption":1539.0746,"timestamp":1752650764.6232946,"container":null},{"exe":"/home/youssef/.asdf/installs/python/3.12.3/bin/python3.12","cmdline":"/home/youssef/web-server-benchmarks/srv/bin/python3./containers/measure_docker.py--server_imagest-cowboy-27-self--port_mapping8001:80--num_requests10000--output_csvresults/2025-07-16_090602/static/st-cowboy-27-self.csv","pid":60449,"resources_usage":null,"consumption":1539.0746,"timestamp":1752650764.6233065,"container":null},{"exe":"","cmdline":"","pid":6,"resources_usage":null,"consumption":0.0,"timestamp":1752650764.6232738,"container":null},{"exe":"/usr/lib/xorg/Xorg","cmdline":"/usr/lib/xorg/Xorgvt2-displayfd3-auth/run/user/1000/gdm/Xauthority-nolistentcp-backgroundnone-noreset-keeptty-novtswitch-verbose3","pid":1680,"resources_usage":null,"consumption":0.0,"timestamp":1752650764.623275,"container":null},{"exe":"/usr/sbin/cron","cmdline":"/usr/sbin/cron-f","pid":675,"resources_usage":null,"consumption":0.0,"timestamp":1752650764.6232765,"container":null},{"exe":"","cmdline":"","pid":171,"resources_usage":null,"consumption":0.0,"timestamp":1752650764.623277,"container":null},{"exe":"","cmdline":"","pid":35,"resources_usage":null,"consumption":0.0,"timestamp":1752650764.6232772,"container":null},{"exe":"/usr/lib/systemd/systemd","cmdline":"(sd-pam)","pid":1613,"resources_usage":null,"consumption":0.0,"timestamp":1752650764.6232777,"container":null},{"exe":"/usr/libexec/at-spi-bus-launcher","cmdline":"/usr/libexec/at-spi-bus-launcher","pid":1943,"resources_usage":null,"consumption":0.0,"timestamp":1752650764.6232784,"container":null}],"sockets":[{"id":0,"consumption":901522.0,"domains":[{"name":"uncore","consumption":0.0,"timestamp":1752650764.596024},{"name":"core","consumption":150920.0,"timestamp":1752650764.595985},{"name":"dram","consumption":283232.0,"timestamp":1752650764.5959415}],"timestamp":1752650764.5954561}]},{"host":{"consumption":2754522.0,"timestamp":1752650766.670712,"components":{"disks":[{"disk_type":"Unknown","disk_mount_point":"/var/lib/docker/overlay2/71ddaf31366dee1c7efc1b8de12a1f706b48c8ce98f254146159398d39d4dafc/merged","disk_is_removable":false,"disk_file_system":"overlay","disk_total_bytes":"204402401280","disk_available_bytes":"151201976320","disk_name":"overlay"}]}},"consumers":[{"exe":"/usr/bin/scaphandre","cmdline":"/usr/bin/scaphandrejson--containers-foutput/2025-07-16-092538.json","pid":60719,"resources_usage":null,"consumption":11778.653,"timestamp":1752650766.6705706,"container":null},{"exe":"/usr/bin/containerd","cmdline":"/usr/bin/containerd","pid":774,"resources_usage":null,"consumption":1682.6647,"timestamp":1752650766.6705205,"container":null},{"exe":"/app/simple_cowboy_app/erts-15.2.7/bin/beam.smp","cmdline":"/app/simple_cowboy_app/bin/simple_cowboy_app-Bd-Cmulti_time_warp---root/app/simple_cowboy_app-bindir/app/simple_cowboy_app/erts-15.2.7/bin-prognameapp/simple_cowboy_app/bin/simple_cowboy_app---home/root---noshell-noinput-boot/app/simple_cowboy_app/releases/0.1.0/start-modeembedded-boot_varSYSTEM_LIB_DIR/app/simple_cowboy_app/lib-config/app/simple_cowboy_app/releases/0.1.0/sys.config-snamesimple_cowboy_app-setcookiesimple_cowboy_app----foreground--","pid":60531,"resources_usage":null,"consumption":1682.6647,"timestamp":1752650766.6705735,"container":{"name":"st-cowboy-27-self","id":"9bee05275f2c658d0de20ed3de1f43b99572cc5e727ff38cd1371a8ae1720c93","runtime":"unknown","scheduler":"docker"}},{"exe":"","cmdline":"","pid":6,"resources_usage":null,"consumption":0.0,"timestamp":1752650766.6704934,"container":null},{"exe":"/usr/lib/xorg/Xorg","cmdline":"/usr/lib/xorg/Xorgvt2-displayfd3-auth/run/user/1000/gdm/Xauthority-nolistentcp-backgroundnone-noreset-keeptty-novtswitch-verbose3","pid":1680,"resources_usage":null,"consumption":0.0,"timestamp":1752650766.6704943,"container":null},{"exe":"/usr/sbin/cron","cmdline":"/usr/sbin/cron-f","pid":675,"resources_usage":null,"consumption":0.0,"timestamp":1752650766.6704957,"container":null},{"exe":"","cmdline":"","pid":171,"resources_usage":null,"consumption":0.0,"timestamp":1752650766.6704962,"container":null},{"exe":"","cmdline":"","pid":35,"resources_usage":null,"consumption":0.0,"timestamp":1752650766.6704965,"container":null},{"exe":"/usr/lib/systemd/systemd","cmdline":"(sd-pam)","pid":1613,"resources_usage":null,"consumption":0.0,"timestamp":1752650766.6704967,"container":null},{"exe":"/usr/libexec/at-spi-bus-launcher","cmdline":"/usr/libexec/at-spi-bus-launcher","pid":1943,"resources_usage":null,"consumption":0.0,"timestamp":1752650766.6704977,"container":null}],"sockets":[{"id":0,"consumption":995145.0,"domains":[{"name":"uncore","consumption":9217.0,"timestamp":1752650766.642145},{"name":"core","consumption":216115.0,"timestamp":1752650766.6421032},{"name":"dram","consumption":301130.0,"timestamp":1752650766.6420562}],"timestamp":1752650766.641576}]},{"host":{"consumption":2058828.0,"timestamp":1752650768.7414205,"components":{"disks":[{"disk_type":"Unknown","disk_mount_point":"/var/lib/docker/overlay2/71ddaf31366dee1c7efc1b8de12a1f706b48c8ce98f254146159398d39d4dafc/merged","disk_is_removable":false,"disk_file_system":"overlay","disk_total_bytes":"204402401280","disk_available_bytes":"151201976320","disk_name":"overlay"}]}},"consumers":[{"exe":"/usr/bin/scaphandre","cmdline":"/usr/bin/scaphandrejson--containers-foutput/2025-07-16-092538.json","pid":60719,"resources_usage":null,"consumption":8681.805,"timestamp":1752650768.7412775,"container":null},{"exe":"/usr/lib/xorg/Xorg","cmdline":"/usr/lib/xorg/Xorgvt2-displayfd3-auth/run/user/1000/gdm/Xauthority-nolistentcp-backgroundnone-noreset-keeptty-novtswitch-verbose3","pid":1680,"resources_usage":null,"consumption":1240.2578,"timestamp":1752650768.7411978,"container":null},{"exe":"/usr/bin/gnome-shell","cmdline":"/usr/bin/gnome-shell","pid":1992,"resources_usage":null,"consumption":1240.2578,"timestamp":1752650768.7412581,"container":null},{"exe":"","cmdline":"","pid":43650,"resources_usage":null,"consumption":1240.2578,"timestamp":1752650768.7412734,"container":null},{"exe":"","cmdline":"","pid":6,"resources_usage":null,"consumption":0.0,"timestamp":1752650768.741197,"container":null},{"exe":"/usr/sbin/cron","cmdline":"/usr/sbin/cron-f","pid":675,"resources_usage":null,"consumption":0.0,"timestamp":1752650768.7411995,"container":null},{"exe":"","cmdline":"","pid":171,"resources_usage":null,"consumption":0.0,"timestamp":1752650768.7412,"container":null},{"exe":"","cmdline":"","pid":35,"resources_usage":null,"consumption":0.0,"timestamp":1752650768.7412004,"container":null},{"exe":"/usr/lib/systemd/systemd","cmdline":"(sd-pam)","pid":1613,"resources_usage":null,"consumption":0.0,"timestamp":1752650768.7412007,"container":null},{"exe":"/usr/libexec/at-spi-bus-launcher","cmdline":"/usr/libexec/at-spi-bus-launcher","pid":1943,"resources_usage":null,"consumption":0.0,"timestamp":1752650768.7412012,"container":null}],"sockets":[{"id":0,"consumption":822487.0,"domains":[{"name":"uncore","consumption":6322.0,"timestamp":1752650768.688797},{"name":"core","consumption":137487.0,"timestamp":1752650768.6886249},{"name":"dram","consumption":293156.0,"timestamp":1752650768.688446}],"timestamp":1752650768.6877816}]},{"host":{"consumption":2585681.0,"timestamp":1752650770.7877138,"components":{"disks":[{"disk_type":"Unknown","disk_mount_point":"/var/lib/docker/overlay2/71ddaf31366dee1c7efc1b8de12a1f706b48c8ce98f254146159398d39d4dafc/merged","disk_is_removable":false,"disk_file_system":"overlay","disk_total_bytes":"204402401280","disk_available_bytes":"151201972224","disk_name":"overlay"}]}},"consumers":[{"exe":"/usr/bin/scaphandre","cmdline":"/usr/bin/scaphandrejson--containers-foutput/2025-07-16-092538.json","pid":60719,"resources_usage":null,"consumption":9494.545,"timestamp":1752650770.787613,"container":null},{"exe":"/usr/bin/gnome-shell","cmdline":"/usr/bin/gnome-shell","pid":1992,"resources_usage":null,"consumption":3164.8484,"timestamp":1752650770.7875931,"container":null},{"exe":"","cmdline":"","pid":7389,"resources_usage":null,"consumption":1582.4242,"timestamp":1752650770.7875688,"container":null},{"exe":"/app/simple_cowboy_app/erts-15.2.7/bin/beam.smp","cmdline":"/app/simple_cowboy_app/bin/simple_cowboy_app-Bd-Cmulti_time_warp---root/app/simple_cowboy_app-bindir/app/simple_cowboy_app/erts-15.2.7/bin-prognameapp/simple_cowboy_app/bin/simple_cowboy_app---home/root---noshell-noinput-boot/app/simple_cowboy_app/releases/0.1.0/start-modeembedded-boot_varSYSTEM_LIB_DIR/app/simple_cowboy_app/lib-config/app/simple_cowboy_app/releases/0.1.0/sys.config-snamesimple_cowboy_app-setcookiesimple_cowboy_app----foreground--","pid":60531,"resources_usage":null,"consumption":1582.4242,"timestamp":1752650770.7876158,"container":{"name":"st-cowboy-27-self","id":"9bee05275f2c658d0de20ed3de1f43b99572cc5e727ff38cd1371a8ae1720c93","runtime":"unknown","scheduler":"docker"}},{"exe":"/usr/libexec/gnome-terminal-server","cmdline":"/usr/libexec/gnome-terminal-server","pid":9853,"resources_usage":null,"consumption":1582.4242,"timestamp":1752650770.7876227,"container":null},{"exe":"","cmdline":"","pid":6,"resources_usage":null,"consumption":0.0,"timestamp":1752650770.7875307,"container":null},{"exe":"/usr/lib/xorg/Xorg","cmdline":"/usr/lib/xorg/Xorgvt2-displayfd3-auth/run/user/1000/gdm/Xauthority-nolistentcp-backgroundnone-noreset-keeptty-novtswitch-verbose3","pid":1680,"resources_usage":null,"consumption":0.0,"timestamp":1752650770.7875316,"container":null},{"exe":"/usr/sbin/cron","cmdline":"/usr/sbin/cron-f","pid":675,"resources_usage":null,"consumption":0.0,"timestamp":1752650770.787533,"container":null},{"exe":"","cmdline":"","pid":171,"resources_usage":null,"consumption":0.0,"timestamp":1752650770.7875335,"container":null},{"exe":"","cmdline":"","pid":35,"resources_usage":null,"consumption":0.0,"timestamp":1752650770.787534,"container":null}],"sockets":[{"id":0,"consumption":918366.0,"domains":[{"name":"uncore","consumption":6483.0,"timestamp":1752650770.759929},{"name":"core","consumption":138416.0,"timestamp":1752650770.7597764},{"name":"dram","consumption":286631.0,"timestamp":1752650770.7597077}],"timestamp":1752650770.759153}]}]